plain/tailwind/CHANGELOG.md
plain/tailwind/README.md
plain/tailwind/__init__.py
plain/tailwind/cli.py
plain/tailwind/core.py
plain/tailwind/default_settings.py
plain/tailwind/entrypoints.py
plain/tailwind/templates.py
plain/tailwind/skills/plain-tailwind/SKILL.md
plain/tailwind/templates/tailwind/css.html
plain_tailwind-0.20.0.dist-info/METADATA
plain_tailwind-0.20.0.dist-info/WHEEL
plain_tailwind-0.20.0.dist-info/entry_points.txt
plain_tailwind-0.20.0.dist-info/licenses/LICENSE
plain_tailwind-0.20.0.dist-info/RECORD
