Metadata-Version: 2.4
Name: plain.tailwind
Version: 0.20.0
Summary: Integrate Tailwind CSS without JavaScript or npm.
Author-email: Dave Gaeddert <dave.gaeddert@dropseed.dev>
License-Expression: BSD-3-Clause
License-File: LICENSE
Requires-Python: >=3.13
Requires-Dist: plain<1.0.0
Requires-Dist: requests>=2.0.0
Requires-Dist: tomlkit>=0.12.1
